MANIFEST.in
README.rst
requirements.txt
setup.py
reactive_grpc.egg-info/PKG-INFO
reactive_grpc.egg-info/SOURCES.txt
reactive_grpc.egg-info/dependency_links.txt
reactive_grpc.egg-info/not-zip-safe
reactive_grpc.egg-info/requires.txt
reactive_grpc.egg-info/top_level.txt
rxgrpc/__init__.py
rxgrpc/filters.py
rxgrpc/mappers.py
rxgrpc/operators.py
rxgrpc/server.py
rxgrpc/thread_pool.py