Metadata-Version: 1.1
Name: reactive-grpc
Version: 0.0.2
Summary: Python reactive gRPC support
Home-page: https://github.com/fcracker79/reactive-grpc
Author: fcracker79
Author-email: fcracker79@gmail.com
License: MIT
Keywords: reactive reactive-programming grpc protobuf
Platform: UNKNOWN
Classifier: Development Status :: 3 - Alpha
Classifier: Intended Audience :: Developers
Classifier: Topic :: Software Development
Classifier: License :: OSI Approved :: MIT License
Classifier: Programming Language :: Python :: 3.6
Classifier: Programming Language :: Python :: 3.7
